{
    "id": 4245095,
    "name": "Cosmic Dreamer V2",
    "author": "Toxic GD",
    "creators": [],
    "verifier": "Toxic GD",
    "verification": "https://www.youtube.com/watch?v=EhP_KtN-esw",
    "percentToQualify": "100",
    "password": 363633,
    "records": [
        {
            "user": "SmileBullet",
            "link": "",
            "percent": 100,
            "hz": 60
        },
        {
            "user": "WKGames",
            "link": "",
            "percent": 100,
            "hz": "- "
        },
        {
            "user": "l1ghtning",
            "link": "",
            "percent": 100,
            "hz": 360
        },
        {
            "user": "shenanigans",
            "link": "",
            "percent": 100,
            "hz": 360
        },
        {
            "user": "DIUS3D",
            "link": "",
            "percent": 100,
            "hz": 120
        },
        {
            "user": "Arcadie",
            "link": "https://youtu.be/dMvsuUFeCcQ",
            "percent": 100,
            "hz": 240
        },
        {
            "user": "Kuzdavo",
            "link": "",
            "percent": 100,
            "hz": 60
        },
        {
            "user": "Big",
            "link": "",
            "percent": 100,
            "hz": 144
        },
        {
            "user": "rommydash",
            "link": "",
            "percent": 100,
            "hz": "- "
        },
        {
            "user": "goody",
            "link": "https://youtu.be/RfWMSHyMOlk?si=jp-9UTxxBBChJkgX",
            "percent": 100,
            "hz": "- "
        },
        {
            "user": "Sheepyboy",
            "link": "https://youtu.be/gJe7vbgVSF8?si=gtmvxvpmwNMcU3Fi",
            "percent": 100,
            "hz": "- "
        },
        {
            "user": "zzoink15",
            "link": "",
            "percent": 100,
            "hz": "- "
        },
        {
            "user": "nukakulah",
            "link": "",
            "percent": 100,
            "hz": 60
        },
        {
            "user": "Cearulyze",
            "link": "",
            "percent": 100,
            "hz": "- "
        },
        {
            "user": "TheoSi",
            "link": "",
            "percent": 100,
            "hz": "- "
        },
        {
            "user": "Subw1",
            "link": "",
            "percent": 100,
            "hz": "- "
        },
        {
            "user": "Chahnkeh",
            "link": "",
            "percent": 100,
            "hz": "- "
        },
        {
            "user": "kuba",
            "link": "",
            "percent": 100,
            "hz": 120
        },
        {
            "user": "ZircleZ",
            "link": "",
            "percent": 100,
            "hz": "- "
        },
        {
            "user": "Soulbound",
            "link": "",
            "percent": 100,
            "hz": "- "
        },
        {
            "user": "JoacoPe",
            "link": "",
            "percent": 100,
            "hz": 120
        },
        {
            "user": "yzae",
            "link": "",
            "percent": 100,
            "hz": 360
        },
        {
            "user": "SkyHigh",
            "link": "",
            "percent": 100,
            "hz": "- "
        },
        {
            "user": "POKEMON GD",
            "link": "",
            "percent": 100,
            "hz": "- "
        },
        {
            "user": "Starfruit",
            "link": "",
            "percent": 100,
            "hz": "- "
        },
        {
            "user": "cupcake",
            "link": "",
            "percent": 100,
            "hz": "- "
        },
        {
            "user": "dashy6283",
            "link": "",
            "percent": 100,
            "hz": "- "
        },
        {
            "user": "Wide Shady",
            "link": "",
            "percent": 100,
            "hz": "- "
        },
        {
            "user": "ThayLoser",
            "link": "",
            "percent": 100,
            "hz": "- "
        },
        {
            "user": "tomm",
            "link": "",
            "percent": 100,
            "hz": "- "
        },
        {
            "user": "RoboBear04",
            "link": "",
            "percent": 100,
            "hz": 120
        },
        {
            "user": "gtdm",
            "link": "",
            "percent": 100,
            "hz": "- "
        },
        {
            "user": "Jarzst",
            "link": "",
            "percent": 100,
            "hz": "- "
        },
        {
            "user": "Music addict",
            "link": "",
            "percent": 100,
            "hz": "- "
        }
    ]
}