{
    "id": 62964138,
    "name": "Jive (P)",
    "author": "Toughfey",
    "creators": [],
    "verifier": "Toughfey",
    "verification": "https://youtu.be/xGw1ES_G2_M",
    "percentToQualify": "100",
    "password": "Free to Copy",
    "records": [
        {
            "user": "sigmaexe",
            "link": "",
            "percent": 100,
            "hz": "- "
        },
        {
            "user": "DIUS3D",
            "link": "",
            "percent": 100,
            "hz": "- "
        },
        {
            "user": "CtrlZ",
            "link": "",
            "percent": 100,
            "hz": 360
        },
        {
            "user": "Anomaly",
            "link": "",
            "percent": 100,
            "hz": "- "
        },
        {
            "user": "Starfruit",
            "link": "",
            "percent": 100,
            "hz": "- "
        },
        {
            "user": "StellarGradient",
            "link": "",
            "percent": 100,
            "hz": "- "
        },
        {
            "user": "l1ghtning",
            "link": "",
            "percent": 100,
            "hz": 360
        },
        {
            "user": "RelieV",
            "link": "",
            "percent": 100,
            "hz": 90
        },
        {
            "user": "cupcake",
            "link": "",
            "percent": 100,
            "hz": "- "
        },
        {
            "user": "stickch",
            "link": "",
            "percent": 100,
            "hz": "- "
        },
        {
            "user": "Abeginner",
            "link": "",
            "percent": 100,
            "hz": 240
        },
        {
            "user": "Big",
            "link": "",
            "percent": 100,
            "hz": 144
        },
        {
            "user": "Kuzdavo",
            "link": "",
            "percent": 100,
            "hz": 60
        },
        {
            "user": "FireBird",
            "link": "",
            "percent": 100,
            "hz": 360
        },
        {
            "user": "Ireane",
            "link": "",
            "percent": 100,
            "hz": "- "
        },
        {
            "user": "rommydash",
            "link": "",
            "percent": 100,
            "hz": "- "
        },
        {
            "user": "Stallia",
            "link": "",
            "percent": 100,
            "hz": "- "
        },
        {
            "user": "goody",
            "link": "",
            "percent": 100,
            "hz": "- "
        },
        {
            "user": "shenanigans",
            "link": "",
            "percent": 100,
            "hz": 360
        },
        {
            "user": "Sheepyboy",
            "link": "https://youtu.be/OlIi32syJ3Q",
            "percent": 100,
            "hz": "- "
        },
        {
            "user": "POKEMON GD",
            "link": "",
            "percent": 100,
            "hz": "- "
        }
    ]
}