{
    "id": 78798179,
    "name": "totality",
    "author": "gluewis",
    "creators": [],
    "verifier": "gluewis",
    "verification": "https://youtu.be/8xVyq7PgYsc",
    "percentToQualify": "100",
    "password": "Free to Copy",
    "records": [
        {
            "user": "SmackinTheKraken",
            "link": "https://cdn.discordapp.com/attachments/935751594836901899/1138644320346456164/gluewis_totality_100_Easy_Demon.mp4?ex=68a9c168&is=68a86fe8&hm=11ae9a8f89d4b6b129003e670a31db44db6468cebbd0fa17ee8fe9442af7cca6&",
            "percent": 100,
            "hz": 240
        },
        {
            "user": "Ireane",
            "link": "",
            "percent": 100,
            "hz": "- "
        },
        {
            "user": "l1ghtning",
            "link": "",
            "percent": 100,
            "hz": 360
        },
        {
            "user": "DIUS3D",
            "link": "",
            "percent": 100,
            "hz": 120
        },
        {
            "user": "sigmaexe",
            "link": "",
            "percent": 100,
            "hz": "- "
        },
        {
            "user": "Big",
            "link": "",
            "percent": 100,
            "hz": 144
        },
        {
            "user": "JoacoPe",
            "link": "",
            "percent": 100,
            "hz": 120
        },
        {
            "user": "JAYTHEGOAT",
            "link": "",
            "percent": 100,
            "hz": 60
        },
        {
            "user": "Zorktron",
            "link": "",
            "percent": 100,
            "hz": "- "
        },
        {
            "user": "kuba",
            "link": "",
            "percent": 100,
            "hz": 120
        },
        {
            "user": "Sharko",
            "link": "",
            "percent": 100,
            "hz": "- "
        },
        {
            "user": "WKGames",
            "link": "",
            "percent": 100,
            "hz": "- "
        },
        {
            "user": "tomm",
            "link": "",
            "percent": 100,
            "hz": "- "
        },
        {
            "user": "POKEMON GD",
            "link": "https://youtu.be/4Pu-pHUXEaE?si=1kYApIkiUkP02Tuy",
            "percent": 100,
            "hz": "- "
        },
        {
            "user": "CoriOshawott",
            "link": "",
            "percent": 100,
            "hz": "- "
        },
        {
            "user": "nukakulah",
            "link": "",
            "percent": 100,
            "hz": "- "
        },
        {
            "user": "Chonkey",
            "link": "",
            "percent": 100,
            "hz": "- "
        },
        {
            "user": "SkyHigh",
            "link": "",
            "percent": 100,
            "hz": "- "
        },
        {
            "user": "AMB1008",
            "link": "",
            "percent": 100,
            "hz": "- "
        },
        {
            "user": "Cearulyze",
            "link": "",
            "percent": 100,
            "hz": "- "
        },
        {
            "user": "ZircleZ",
            "link": "",
            "percent": 100,
            "hz": "- "
        },
        {
            "user": "Beeshie",
            "link": "",
            "percent": 100,
            "hz": "- "
        },
        {
            "user": "wassas1",
            "link": "",
            "percent": 100,
            "hz": "- "
        },
        {
            "user": "Arcadie",
            "link": "",
            "percent": 100,
            "hz": "- "
        },
        {
            "user": "shiver",
            "link": "",
            "percent": 100,
            "hz": "- "
        },
        {
            "user": "Maverix",
            "link": "",
            "percent": 100,
            "hz": "- "
        },
        {
            "user": "RoboBear04",
            "link": "",
            "percent": 100,
            "hz": 120
        },
        {
            "user": "TheoSi",
            "link": "",
            "percent": 100,
            "hz": "- "
        },
        {
            "user": "Chonkey",
            "link": "",
            "percent": 100,
            "hz": "- "
        },
        {
            "user": "Bottomless",
            "link": "",
            "percent": 100,
            "hz": 240
        },
        {
            "user": "AerialShard",
            "link": "",
            "percent": 100,
            "hz": 60
        }
    ]
}