{
    "id": 109411209,
    "name": "Tungsten Cube",
    "author": "MrPoopyBurger",
    "creators": [],
    "verifier": "MrPoopyBurger",
    "verification": "https://youtu.be/T44uQ5fySvo",
    "percentToQualify": "100",
    "password": "Free to Copy",
    "records": [
        {
            "user": "ZircleZ",
            "link": "",
            "percent": 100,
            "hz": 60
        },
        {
            "user": "tomm",
            "link": "",
            "percent": 100,
            "hz": "- "
        },
        {
            "user": "DaShahzad",
            "link": "",
            "percent": 100,
            "hz": "- "
        },
        {
            "user": "l1ghtning",
            "link": "",
            "percent": 100,
            "hz": 360
        },
        {
            "user": "CoriOshawott",
            "link": "",
            "percent": 100,
            "hz": "- "
        },
        {
            "user": "AerialShard",
            "link": "",
            "percent": 100,
            "hz": "- "
        },
        {
            "user": "dashy6283",
            "link": "",
            "percent": 100,
            "hz": 60
        },
        {
            "user": "nukakulah",
            "link": "",
            "percent": 100,
            "hz": 360
        },
        {
            "user": "POKEMON GD",
            "link": "",
            "percent": 100,
            "hz": "- "
        },
        {
            "user": "carso",
            "link": "",
            "percent": 100,
            "hz": "- "
        },
        {
            "user": "Sheepyboy",
            "link": "",
            "percent": 100,
            "hz": 144
        },
        {
            "user": "DIUS3D",
            "link": "",
            "percent": 100,
            "hz": 120
        },
        {
            "user": "StellarGradient",
            "link": "",
            "percent": 100,
            "hz": "- "
        },
        {
            "user": "AceK58",
            "link": "",
            "percent": 100,
            "hz": "- "
        },
        {
            "user": "SkyHigh",
            "link": "",
            "percent": 100,
            "hz": 360
        },
        {
            "user": "Big",
            "link": "",
            "percent": 100,
            "hz": 60
        },
        {
            "user": "Cearulyze",
            "link": "",
            "percent": 100,
            "hz": "- "
        },
        {
            "user": "xyne",
            "link": "",
            "percent": 100,
            "hz": "- "
        },
        {
            "user": "TheoSi",
            "link": "",
            "percent": 100,
            "hz": "- "
        },
        {
            "user": "RoboBear04",
            "link": "",
            "percent": 100,
            "hz": 120
        },
        {
            "user": "WKGames",
            "link": "",
            "percent": 100,
            "hz": "- "
        },
        {
            "user": "Chahnkeh",
            "link": "",
            "percent": 100,
            "hz": "- "
        },
        {
            "user": "Music addict",
            "link": "",
            "percent": 100,
            "hz": "- "
        },
        {
            "user": "Jarzst",
            "link": "",
            "percent": 100,
            "hz": "-"
        },
        {
            "user": "krii",
            "link": "",
            "percent": 100,
            "hz": "- "    
        },
        {
            "user": "Cyber",
            "link": "",
            "percent": 100,
            "hz": "- "
        }
    ]
}
